milksnake/__init__.py
milksnake/_compat.py
milksnake/empty.c
milksnake/ffi.py
milksnake/setuptools_ext.py
milksnake-0.1.4.dist-info/DESCRIPTION.rst
milksnake-0.1.4.dist-info/METADATA
milksnake-0.1.4.dist-info/RECORD
milksnake-0.1.4.dist-info/WHEEL
milksnake-0.1.4.dist-info/entry_points.txt
milksnake-0.1.4.dist-info/metadata.json
milksnake-0.1.4.dist-info/top_level.txt
