Metadata-Version: 2.0
Name: milksnake
Version: 0.1.4
Summary: A python library that extends setuptools for binary extensions.
Home-page: UNKNOWN
Author: Armin Ronacher
Author-email: armin.ronacher@active-4.com
License: Apache License 2.0
Platform: any
Classifier: License :: OSI Approved :: Apache Software License
Classifier: Programming Language :: Python
Requires-Dist: cffi (>=1.6.0)
